README.rst
setup.py
mljar/__init__.py
mljar/exceptions.py
mljar/log.py
mljar/mljar.py
mljar/utils.py
mljar.egg-info/PKG-INFO
mljar.egg-info/SOURCES.txt
mljar.egg-info/dependency_links.txt
mljar.egg-info/requires.txt
mljar.egg-info/top_level.txt
mljar/client/__init__.py
mljar/client/base.py
mljar/client/dataset.py
mljar/client/dataupload.py
mljar/client/experiment.py
mljar/client/prediction.py
mljar/client/prediction_download.py
mljar/client/predictjob.py
mljar/client/project.py
mljar/client/result.py
mljar/model/__init__.py
mljar/model/base.py
mljar/model/dataset.py
mljar/model/experiment.py
mljar/model/prediction.py
mljar/model/project.py
mljar/model/result.py