Metadata-Version: 1.1
Name: mljar
Version: 0.0.9
Summary: Python wrapper over MLJAR API
Home-page: https://github.com/mljar/mljar-api-python
Author: Piotr Plonski
Author-email: contact@mljar.com
License: Apache-2.0
Platform: UNKNOWN
Classifier: Programming Language :: Python
Classifier: Programming Language :: Python :: 2.7
Classifier: Programming Language :: Python :: 3.6
